tornado_m2crypto/__init__.py
tornado_m2crypto/m2httputil.py
tornado_m2crypto/m2iostream.py
tornado_m2crypto/m2netutil.py
tornado_m2crypto/test/__init__.py
tornado_m2crypto/test/client_test.py
tornado_m2crypto/test/m2io_dirac.py
tornado_m2crypto/test/m2io_https.py
tornado_m2crypto/test/m2iostream_test.py
tornado_m2crypto/test/runtests.py
tornado_m2crypto-0.1.2.dist-info/LICENSE
tornado_m2crypto-0.1.2.dist-info/METADATA
tornado_m2crypto-0.1.2.dist-info/WHEEL
tornado_m2crypto-0.1.2.dist-info/top_level.txt
tornado_m2crypto-0.1.2.dist-info/RECORD
