Metadata-Version: 2.1
Name: tornado-m2crypto
Version: 0.1.2
Summary: Extension for running tornado with M2Crypto instead of the standard python SSL module
Home-page: https://github.com/DIRACGrid/tornado_m2crypto
License: UNKNOWN
Project-URL: Bug Reports, https://github.com/DIRACGrid/tornado_m2crypto/issues
Project-URL: Source, https://github.com/DIRACGrid/tornado_m2crypto/
Keywords: dirac
Platform: UNKNOWN
Classifier: Development Status :: 4 - Beta
Classifier: License :: OSI Approved :: GNU General Public License v3 or later (GPLv3+)
Requires-Python: >=2.7
License-File: LICENSE
Requires-Dist: m2crypto
Requires-Dist: tornado
Requires-Dist: enum34 ; python_version < "3.4"
Provides-Extra: testing
Requires-Dist: requests ; extra == 'testing'
